Metadata-Version: 2.1
Name: es2es
Version: 0.1.0
Summary: UNKNOWN
Home-page: https://github.com/nesta/es2es
Author: Joel Klinger
Author-email: joel.klinger@nesta.org.uk
Maintainer: Joel Klinger
Maintainer-email: joel.klinger@nesta.org.uk
License: MIT
Platform: UNKNOWN
Classifier: Development Status :: 3 - Alpha
Classifier: Intended Audience :: Developers
Classifier: Intended Audience :: Science/Research
Classifier: License :: OSI Approved :: MIT License
Classifier: Natural Language :: English
Classifier: Operating System :: OS Independent
Classifier: Programming Language :: Python :: 3.6
Requires-Python: >3.6
